retryer/__init__.py
retryer/retryer.py
retryer-1.0.4.dist-info/LICENSE
retryer-1.0.4.dist-info/METADATA
retryer-1.0.4.dist-info/WHEEL
retryer-1.0.4.dist-info/top_level.txt
retryer-1.0.4.dist-info/RECORD
