Metadata-Version: 2.1
Name: retryer
Version: 1.0.4
Summary: A retry decorator for error handling
Author: Vishwanath Kannan
License-File: LICENSE
Requires-Dist: time
Requires-Dist: functools
